crccheck/__init__.py
crccheck/base.py
crccheck/checksum.py
crccheck/crc.py
tests/__init__.py
tests/benchmark.py
tests/test_base.py
tests/test_checksum.py
tests/test_crc.py
tests/test_reflectbitorder.py
crccheck-1.2.0.dist-info/METADATA
crccheck-1.2.0.dist-info/WHEEL
crccheck-1.2.0.dist-info/top_level.txt
crccheck-1.2.0.dist-info/RECORD
